cheathit/__init__.py
cheathit/analyzer.py
cheathit/cheathit.py
cheathit/file_finder.py
cheathit/ngram.py
cheathit/ngram_collector.py
cheathit/parser.py
cheathit/shared.py
cheathit-1.0.1.dist-info/LICENSE
cheathit-1.0.1.dist-info/METADATA
cheathit-1.0.1.dist-info/WHEEL
cheathit-1.0.1.dist-info/entry_points.txt
cheathit-1.0.1.dist-info/top_level.txt
cheathit-1.0.1.dist-info/RECORD
