Metadata-Version: 2.1
Name: cheathit
Version: 1.0.1
Summary: Plagiarism detection tool for programming assignments
Home-page: https://github.com/danmysak/cheathit
Author: Danylo Mysak
Author-email: danmysak@gmail.com
Project-URL: Bug Tracker, https://github.com/danmysak/cheathit/issues
Classifier: Programming Language :: Python :: 3
Classifier: License :: OSI Approved :: MIT License
Classifier: Operating System :: OS Independent
Requires-Python: >=3.9
License-File: LICENSE
